HydRa/HydRa2_0_predict.py
HydRa/HydRa_predict.py
HydRa/__init__.py
HydRa/test_data_load.py
HydRa/data/Classification_cv_scores_AllRuns_SONAR+_final_Ensemble_17_3_7_3_combined10RBPlist_menthaBioPlex_STRING.tsv
HydRa/data/Classification_cv_scores_AllRuns_SONAR+_final_Ensemble_17_3_7_3_combined10RBPlist_noSS_menthaBioPlex_STRING.tsv
HydRa/data/Classification_scores_Final_Model_v4_7_3_MenthaBioPlex_STRING_AddingOOPSXRNAXlabels_AddNoSS_trainedWithWholeDataset.xls
HydRa/data/Classification_scores_Final_Model_v4_7_3_MenthaBioPlex_STRING_AddingOOPSXRNAXlabels_noSS_trainedWithWholeDataset.tsv
HydRa/data/Classification_scores_Final_Model_v4_7_3_MenthaBioPlex_STRING_AddingOOPSXRNAXlabels_trainedWithWholeDataset.tsv
HydRa/data/Classification_scores_TrainingWithTheWholeProteinSet_final_model_HydRa2.0_DNN_SVM_ProteinBERT_menthaBioPlex_STRING.tsv
HydRa/data/Classification_scores_TrainingWithTheWholeProteinSet_final_model_HydRa2.0_DNN_SVM_ProteinBERT_menthaBioPlex_STRING_noSS.tsv
HydRa/data/Classification_scores_TrainingWithTheWholeProteinSet_final_model_HydRa2.0_DNN_SVM_ProteinBERT_menthaBioPlex_STRING_noSS.tsv.bk
HydRa/data/Classification_scores_reference_cv_HydRa2.0_DNN_SVM_ProteinBERT_menthaBioPlex_STRING.tsv
HydRa/data/Classification_scores_reference_cv_HydRa2.0_DNN_SVM_ProteinBERT_menthaBioPlex_STRING_noSS.tsv
HydRa/data/Combined10RBPlist_uniprotID_20190716.txt
HydRa/data/Combined8RBPlist_plusOOPSXRNAXsharedRBPs_uniprotID_20190717.txt
HydRa/data/FromOrelOcclRun_Occlusion_maps_seqSVM_seqDNN_scores_statistics.pkl
HydRa/data/HydRa2.0_noSS_Occlusion_maps_seqSVM_seqDNN_ProteinBERT_proteinLengthWiseFib_avg_zscores_statistics.pkl
HydRa/data/HydRa2.0_noSS_Occlusion_maps_seqSVM_seqDNN_ProteinBERT_proteinLengthWiseFib_scores_statistics.pkl
HydRa/data/HydRa2.0_proteins_with_RBP_categories_RBPflagCorrected_Nov2021_new.tsv
HydRa/data/HydRa_v4_7_3_Occlusion_maps_seqSVM_seqDNN_scores_statistics.pkl
HydRa/data/STRING_v10.5_uniprot_edgelist_withoutExperimentalData.txt
hydra_rbp-0.1.21.38.dist-info/LICENSE
hydra_rbp-0.1.21.38.dist-info/METADATA
hydra_rbp-0.1.21.38.dist-info/WHEEL
hydra_rbp-0.1.21.38.dist-info/entry_points.txt
hydra_rbp-0.1.21.38.dist-info/top_level.txt
hydra_rbp-0.1.21.38.dist-info/RECORD
