Metadata-Version: 2.1
Name: hydra-rbp
Version: 0.1.21.38
Summary: A hybrid ensemble classifier for RNA-binding proteins utilizing protein-protein interaction context and protein sequence features.
Home-page: https://github.com/Wenhao-Jin/HydRa
Author: Wenhao Jin
Author-email: vincenzojin@gmail.com
Keywords: RNA-binding proteins,prediction,CNN,SVM,PPI,bioinformatics
Classifier: Programming Language :: Python :: 3
Classifier: License :: OSI Approved :: MIT License
Classifier: Operating System :: OS Independent
Requires-Python: >=3.6
License-File: LICENSE
Requires-Dist: setuptools
Requires-Dist: pandas
Requires-Dist: numpy
Requires-Dist: networkx >=2.0
Requires-Dist: scikit-learn <0.23.1,>=0.22.1
Requires-Dist: tensorflow >=2.3.1
Requires-Dist: keras <2.7.0,>=2.4.3
Requires-Dist: matplotlib
Requires-Dist: protein-bert
